{
  "exchange": {
    "success":true,
    "timestamp":1530238449,
    "base":"EUR",
    "date":"2018-06-29",
    "rates":{
      "AED":4.250311,
      "AFN":84.689553,
      "ALL":125.679624,
      "AMD":557.306984,
      "ANG":2.094452,
      "AOA":288.129231,
      "ARS":32.367656,
      "AUD":1.575396,
      "AWG":2.059942,
      "AZN":1.966782,
      "BAM":1.959289,
      "BBD":2.314542,
      "BDT":96.759426,
      "BGN":1.954046,
      "BHD":0.436759,
      "BIF":2026.358281,
      "BMD":1.157271,
      "BND":1.566139,
      "BOB":7.938883,
      "BRL":4.468801,
      "BSD":1.157271,
      "BTC":0.000197,
      "BTN":79.330928,
      "BWP":12.112231,
      "BYN":2.314323,
      "BYR":22682.510804,
      "BZD":2.312,
      "CAD":1.534843,
      "CDF":1811.726218,
      "CHF":1.154216,
      "CLF":0.027393,
      "CLP":751.381339,
      "CNY":7.67895,
      "COP":3408.741611,
      "CRC":652.399919,
      "CUC":1.157271,
      "CUP":30.66768,
      "CVE":110.299493,
      "CZK":25.931548,
      "DJF":205.41597,
      "DKK":7.454874,
      "DOP":57.088179,
      "DZD":136.141355,
      "EGP":20.645468,
      "ERN":17.671488,
      "ETB":31.477771,
      "EUR":1,
      "FJD":2.420549,
      "FKP":0.884616,
      "GBP":0.885267,
      "GEL":2.827789,
      "GGP":0.885268,
      "GHS":5.518446,
      "GIP":0.884966,
      "GMD":54.079509,
      "GNF":10416.595326,
      "GTQ":8.670854,
      "GYD":238.501967,
      "HKD":9.080526,
      "HNL":27.655303,
      "HRK":7.320319,
      "HTG":75.720877,
      "HUF":328.653368,
      "IDR":16676.274525,
      "ILS":4.22971,
      "IMP":0.885268,
      "INR":79.654962,
      "IQD":1370.208816,
      "IRR":49288.170427,
      "ISK":123.943717,
      "JEP":0.885268,
      "JMD":149.727723,
      "JOD":0.819928,
      "JPY":127.854134,
      "KES":116.710774,
      "KGS":78.839897,
      "KHR":4651.766462,
      "KMF":487.650843,
      "KPW":1041.543465,
      "KRW":1295.566727,
      "KWD":0.34973,
      "KYD":0.949634,
      "KZT":394.467362,
      "LAK":9723.390688,
      "LBP":1742.269766,
      "LKR":183.080262,
      "LRD":172.178772,
      "LSL":16.016969,
      "LTL":3.52817,
      "LVL":0.718145,
      "LYD":1.589513,
      "MAD":11.038746,
      "MDL":19.503489,
      "MGA":3784.276041,
      "MKD":61.265923,
      "MMK":1636.381227,
      "MNT":2846.886677,
      "MOP":9.353873,
      "MRO":410.83117,
      "MUR":39.98371,
      "MVR":18.019054,
      "MWK":825.65498,
      "MXN":22.828326,
      "MYR":4.678818,
      "MZN":67.96678,
      "NAD":15.954124,
      "NGN":413.145998,
      "NIO":36.164368,
      "NOK":9.477241,
      "NPR":127.357673,
      "NZD":1.71658,
      "OMR":0.44543,
      "PAB":1.157271,
      "PEN":3.785662,
      "PGK":3.751297,
      "PHP":61.879279,
      "PKR":140.573705,
      "PLN":4.362451,
      "PYG":6544.366971,
      "QAR":4.212232,
      "RON":4.658242,
      "RSD":117.825577,
      "RUB":72.709019,
      "RWF":983.020663,
      "SAR":4.339882,
      "SBD":9.203663,
      "SCR":15.516722,
      "SDG":20.779028,
      "SEK":10.44665,
      "SGD":1.583124,
      "SHP":0.884969,
      "SLL":9258.167711,
      "SOS":660.801939,
      "SRD":8.574994,
      "STD":24509.956924,
      "SVC":10.126371,
      "SYP":595.971376,
      "SZL":15.963974,
      "THB":38.421397,
      "TJS":10.597013,
      "TMT":3.934721,
      "TND":3.029161,
      "TOP":2.680358,
      "TRY":5.311292,
      "TTD":7.695278,
      "TWD":35.371988,
      "TZS":2625.848228,
      "UAH":30.413082,
      "UGX":4483.499094,
      "USD":1.157271,
      "UYU":36.280779,
      "UZS":9084.576919,
      "VEF":110820.267439,
      "VND":26540.852183,
      "VUV":126.073101,
      "WST":3.013994,
      "XAF":655.617167,
      "XAG":0.072449,
      "XAU":0.000928,
      "XCD":3.122618,
      "XDR":0.823727,
      "XOF":655.617167,
      "XPF":119.356794,
      "YER":289.202006,
      "ZAR":15.968371,
      "ZMK":10416.827308,
      "ZMW":11.503531,
      "ZWL":373.052093
    }
  }
}
